[{"bounding_box": {"minimum": {"r": 504, "c": 1493}, "maximum": {"r": 609, "c": 1594}}, "category": "red blood cell"}, {"bounding_box": {"minimum": {"r": 768, "c": 620}, "maximum": {"r": 882, "c": 732}}, "category": "red blood cell"}, {"bounding_box": {"minimum": {"r": 228, "c": 1252}, "maximum": {"r": 332, "c": 1346}}, "category": "red blood cell"}, {"bounding_box": {"minimum": {"r": 284, "c": 132}, "maximum": {"r": 393, "c": 240}}, "category": "red blood cell"}, {"bounding_box": {"minimum": {"r": 468, "c": 1287}, "maximum": {"r": 564, "c": 1403}}, "category": "red blood cell"}, {"bounding_box": {"minimum": {"r": 123, "c": 1053}, "maximum": {"r": 249, "c": 1170}}, "category": "red blood cell"}, {"bounding_box": {"minimum": {"r": 350, "c": 744}, "maximum": {"r": 472, "c": 857}}, "category": "red blood cell"}, {"bounding_box": {"minimum": {"r": 379, "c": 948}, "maximum": {"r": 495, "c": 1035}}, "category": "red blood cell"}, {"bounding_box": {"minimum": {"r": 900, "c": 460}, "maximum": {"r": 1024, "c": 569}}, "category": "red blood cell"}, {"bounding_box": {"minimum": {"r": 12, "c": 1282}, "maximum": {"r": 126, "c": 1387}}, "category": "red blood cell"}, {"bounding_box": {"minimum": {"r": 672, "c": 669}, "maximum": {"r": 776, "c": 773}}, "category": "red blood cell"}, {"bounding_box": {"minimum": {"r": 363, "c": 1268}, "maximum": {"r": 460, "c": 1383}}, "category": "red blood cell"}, {"bounding_box": {"minimum": {"r": 164, "c": 951}, "maximum": {"r": 276, "c": 1068}}, "category": "red blood cell"}, {"bounding_box": {"minimum": {"r": 400, "c": 1024}, "maximum": {"r": 517, "c": 1131}}, "category": "red blood cell"}, {"bounding_box": {"minimum": {"r": 485, "c": 370}, "maximum": {"r": 602, "c": 495}}, "category": "red blood cell"}, {"bounding_box": {"minimum": {"r": 853, "c": 372}, "maximum": {"r": 953, "c": 479}}, "category": "red blood cell"}, {"bounding_box": {"minimum": {"r": 388, "c": 841}, "maximum": {"r": 511, "c": 950}}, "category": "red blood cell"}, {"bounding_box": {"minimum": {"r": 875, "c": 114}, "maximum": {"r": 985, "c": 231}}, "category": "red blood cell"}, {"bounding_box": {"minimum": {"r": 539, "c": 247}, "maximum": {"r": 647, "c": 363}}, "category": "red blood cell"}, {"bounding_box": {"minimum": {"r": 912, "c": 1230}, "maximum": {"r": 1017, "c": 1342}}, "category": "red blood cell"}, {"bounding_box": {"minimum": {"r": 478, "c": 1066}, "maximum": {"r": 605, "c": 1187}}, "category": "red blood cell"}, {"bounding_box": {"minimum": {"r": 94, "c": 885}, "maximum": {"r": 204, "c": 1006}}, "category": "red blood cell"}, {"bounding_box": {"minimum": {"r": 784, "c": 740}, "maximum": {"r": 891, "c": 844}}, "category": "red blood cell"}, {"bounding_box": {"minimum": {"r": 112, "c": 1195}, "maximum": {"r": 203, "c": 1326}}, "category": "red blood cell"}, {"bounding_box": {"minimum": {"r": 263, "c": 1467}, "maximum": {"r": 377, "c": 1589}}, "category": "red blood cell"}, {"bounding_box": {"minimum": {"r": 458, "c": 224}, "maximum": {"r": 560, "c": 341}}, "category": "red blood cell"}, {"bounding_box": {"minimum": {"r": 834, "c": 1456}, "maximum": {"r": 949, "c": 1564}}, "category": "red blood cell"}, {"bounding_box": {"minimum": {"r": 637, "c": 1202}, "maximum": {"r": 740, "c": 1346}}, "category": "red blood cell"}, {"bounding_box": {"minimum": {"r": 836, "c": 1172}, "maximum": {"r": 954, "c": 1302}}, "category": "red blood cell"}, {"bounding_box": {"minimum": {"r": 846, "c": 1293}, "maximum": {"r": 962, "c": 1419}}, "category": "red blood cell"}, {"bounding_box": {"minimum": {"r": 766, "c": 1349}, "maximum": {"r": 868, "c": 1472}}, "category": "red blood cell"}, {"bounding_box": {"minimum": {"r": 178, "c": 7}, "maximum": {"r": 304, "c": 119}}, "category": "red blood cell"}, {"bounding_box": {"minimum": {"r": 896, "c": 553}, "maximum": {"r": 1036, "c": 652}}, "category": "red blood cell"}, {"bounding_box": {"minimum": {"r": 532, "c": 1145}, "maximum": {"r": 649, "c": 1264}}, "category": "red blood cell"}, {"bounding_box": {"minimum": {"r": 796, "c": 70}, "maximum": {"r": 924, "c": 192}}, "category": "red blood cell"}, {"bounding_box": {"minimum": {"r": 962, "c": 327}, "maximum": {"r": 1063, "c": 460}}, "category": "red blood cell"}, {"bounding_box": {"minimum": {"r": 860, "c": 971}, "maximum": {"r": 972, "c": 1083}}, "category": "red blood cell"}, {"bounding_box": {"minimum": {"r": 299, "c": 864}, "maximum": {"r": 395, "c": 1019}}, "category": "red blood cell"}]