[{"bounding_box": {"minimum": {"r": 322, "c": 1396}, "maximum": {"r": 431, "c": 1510}}, "category": "red blood cell"}, {"bounding_box": {"minimum": {"r": 969, "c": 751}, "maximum": {"r": 1089, "c": 875}}, "category": "red blood cell"}, {"bounding_box": {"minimum": {"r": 591, "c": 544}, "maximum": {"r": 690, "c": 638}}, "category": "red blood cell"}, {"bounding_box": {"minimum": {"r": 924, "c": 464}, "maximum": {"r": 1035, "c": 581}}, "category": "red blood cell"}, {"bounding_box": {"minimum": {"r": 966, "c": 1000}, "maximum": {"r": 1056, "c": 1094}}, "category": "red blood cell"}, {"bounding_box": {"minimum": {"r": 916, "c": 894}, "maximum": {"r": 1023, "c": 998}}, "category": "red blood cell"}, {"bounding_box": {"minimum": {"r": 22, "c": 166}, "maximum": {"r": 125, "c": 290}}, "category": "red blood cell"}, {"bounding_box": {"minimum": {"r": 316, "c": 688}, "maximum": {"r": 408, "c": 791}}, "category": "red blood cell"}, {"bounding_box": {"minimum": {"r": 462, "c": 182}, "maximum": {"r": 574, "c": 297}}, "category": "red blood cell"}, {"bounding_box": {"minimum": {"r": 854, "c": 1282}, "maximum": {"r": 979, "c": 1408}}, "category": "red blood cell"}, {"bounding_box": {"minimum": {"r": 59, "c": 503}, "maximum": {"r": 174, "c": 613}}, "category": "red blood cell"}, {"bounding_box": {"minimum": {"r": 1040, "c": 1368}, "maximum": {"r": 1145, "c": 1478}}, "category": "red blood cell"}, {"bounding_box": {"minimum": {"r": 83, "c": 1143}, "maximum": {"r": 176, "c": 1255}}, "category": "red blood cell"}, {"bounding_box": {"minimum": {"r": 904, "c": 1}, "maximum": {"r": 1015, "c": 97}}, "category": "red blood cell"}, {"bounding_box": {"minimum": {"r": 220, "c": 972}, "maximum": {"r": 343, "c": 1080}}, "category": "red blood cell"}, {"bounding_box": {"minimum": {"r": 536, "c": 953}, "maximum": {"r": 645, "c": 1054}}, "category": "red blood cell"}, {"bounding_box": {"minimum": {"r": 234, "c": 620}, "maximum": {"r": 334, "c": 723}}, "category": "red blood cell"}, {"bounding_box": {"minimum": {"r": 397, "c": 385}, "maximum": {"r": 504, "c": 500}}, "category": "red blood cell"}, {"bounding_box": {"minimum": {"r": 185, "c": 1484}, "maximum": {"r": 299, "c": 1599}}, "category": "red blood cell"}, {"bounding_box": {"minimum": {"r": 1031, "c": 1080}, "maximum": {"r": 1154, "c": 1208}}, "category": "trophozoite"}, {"bounding_box": {"minimum": {"r": 141, "c": 1133}, "maximum": {"r": 259, "c": 1240}}, "category": "red blood cell"}, {"bounding_box": {"minimum": {"r": 745, "c": 120}, "maximum": {"r": 842, "c": 213}}, "category": "red blood cell"}, {"bounding_box": {"minimum": {"r": 1076, "c": 586}, "maximum": {"r": 1179, "c": 690}}, "category": "red blood cell"}, {"bounding_box": {"minimum": {"r": 455, "c": 872}, "maximum": {"r": 561, "c": 979}}, "category": "red blood cell"}, {"bounding_box": {"minimum": {"r": 941, "c": 1193}, "maximum": {"r": 1061, "c": 1301}}, "category": "red blood cell"}, {"bounding_box": {"minimum": {"r": 98, "c": 1409}, "maximum": {"r": 221, "c": 1527}}, "category": "red blood cell"}, {"bounding_box": {"minimum": {"r": 714, "c": 1483}, "maximum": {"r": 805, "c": 1574}}, "category": "red blood cell"}, {"bounding_box": {"minimum": {"r": 576, "c": 176}, "maximum": {"r": 679, "c": 291}}, "category": "red blood cell"}, {"bounding_box": {"minimum": {"r": 492, "c": 354}, "maximum": {"r": 601, "c": 467}}, "category": "red blood cell"}, {"bounding_box": {"minimum": {"r": 724, "c": 494}, "maximum": {"r": 823, "c": 602}}, "category": "red blood cell"}, {"bounding_box": {"minimum": {"r": 698, "c": 309}, "maximum": {"r": 816, "c": 424}}, "category": "red blood cell"}, {"bounding_box": {"minimum": {"r": 614, "c": 834}, "maximum": {"r": 717, "c": 956}}, "category": "red blood cell"}, {"bounding_box": {"minimum": {"r": 391, "c": 992}, "maximum": {"r": 496, "c": 1114}}, "category": "red blood cell"}, {"bounding_box": {"minimum": {"r": 285, "c": 376}, "maximum": {"r": 385, "c": 491}}, "category": "red blood cell"}, {"bounding_box": {"minimum": {"r": 803, "c": 1443}, "maximum": {"r": 901, "c": 1544}}, "category": "red blood cell"}, {"bounding_box": {"minimum": {"r": 490, "c": 1085}, "maximum": {"r": 589, "c": 1191}}, "category": "red blood cell"}, {"bounding_box": {"minimum": {"r": 7, "c": 802}, "maximum": {"r": 100, "c": 892}}, "category": "red blood cell"}, {"bounding_box": {"minimum": {"r": 1053, "c": 211}, "maximum": {"r": 1150, "c": 311}}, "category": "red blood cell"}, {"bounding_box": {"minimum": {"r": 414, "c": 263}, "maximum": {"r": 521, "c": 373}}, "category": "red blood cell"}, {"bounding_box": {"minimum": {"r": 85, "c": 389}, "maximum": {"r": 197, "c": 498}}, "category": "red blood cell"}, {"bounding_box": {"minimum": {"r": 443, "c": 1287}, "maximum": {"r": 550, "c": 1386}}, "category": "red blood cell"}, {"bounding_box": {"minimum": {"r": 731, "c": 709}, "maximum": {"r": 839, "c": 819}}, "category": "red blood cell"}, {"bounding_box": {"minimum": {"r": 66, "c": 43}, "maximum": {"r": 156, "c": 121}}, "category": "red blood cell"}, {"bounding_box": {"minimum": {"r": 469, "c": 1439}, "maximum": {"r": 560, "c": 1533}}, "category": "red blood cell"}, {"bounding_box": {"minimum": {"r": 464, "c": 68}, "maximum": {"r": 559, "c": 152}}, "category": "red blood cell"}, {"bounding_box": {"minimum": {"r": 1088, "c": 342}, "maximum": {"r": 1188, "c": 441}}, "category": "red blood cell"}, {"bounding_box": {"minimum": {"r": 301, "c": 912}, "maximum": {"r": 396, "c": 1013}}, "category": "red blood cell"}, {"bounding_box": {"minimum": {"r": 909, "c": 1078}, "maximum": {"r": 998, "c": 1163}}, "category": "red blood cell"}, {"bounding_box": {"minimum": {"r": 994, "c": 352}, "maximum": {"r": 1091, "c": 462}}, "category": "red blood cell"}, {"bounding_box": {"minimum": {"r": 332, "c": 321}, "maximum": {"r": 417, "c": 398}}, "category": "red blood cell"}, {"bounding_box": {"minimum": {"r": 700, "c": 805}, "maximum": {"r": 782, "c": 914}}, "category": "red blood cell"}, {"bounding_box": {"minimum": {"r": 780, "c": 418}, "maximum": {"r": 875, "c": 510}}, "category": "red blood cell"}, {"bounding_box": {"minimum": {"r": 1038, "c": 135}, "maximum": {"r": 1141, "c": 246}}, "category": "red blood cell"}, {"bounding_box": {"minimum": {"r": 882, "c": 1180}, "maximum": {"r": 993, "c": 1287}}, "category": "red blood cell"}, {"bounding_box": {"minimum": {"r": 695, "c": 225}, "maximum": {"r": 816, "c": 342}}, "category": "red blood cell"}, {"bounding_box": {"minimum": {"r": 943, "c": 198}, "maximum": {"r": 1057, "c": 310}}, "category": "red blood cell"}, {"bounding_box": {"minimum": {"r": 520, "c": 794}, "maximum": {"r": 624, "c": 900}}, "category": "red blood cell"}, {"bounding_box": {"minimum": {"r": 546, "c": 1376}, "maximum": {"r": 653, "c": 1462}}, "category": "red blood cell"}, {"bounding_box": {"minimum": {"r": 474, "c": 457}, "maximum": {"r": 559, "c": 557}}, "category": "red blood cell"}, {"bounding_box": {"minimum": {"r": 612, "c": 637}, "maximum": {"r": 708, "c": 778}}, "category": "difficult"}, {"bounding_box": {"minimum": {"r": 643, "c": 1381}, "maximum": {"r": 744, "c": 1476}}, "category": "red blood cell"}, {"bounding_box": {"minimum": {"r": 401, "c": 718}, "maximum": {"r": 504, "c": 825}}, "category": "red blood cell"}, {"bounding_box": {"minimum": {"r": 194, "c": 1298}, "maximum": {"r": 292, "c": 1392}}, "category": "red blood cell"}, {"bounding_box": {"minimum": {"r": 637, "c": 1226}, "maximum": {"r": 724, "c": 1354}}, "category": "red blood cell"}, {"bounding_box": {"minimum": {"r": 73, "c": 634}, "maximum": {"r": 164, "c": 726}}, "category": "red blood cell"}, {"bounding_box": {"minimum": {"r": 794, "c": 1133}, "maximum": {"r": 877, "c": 1219}}, "category": "red blood cell"}, {"bounding_box": {"minimum": {"r": 871, "c": 77}, "maximum": {"r": 954, "c": 161}}, "category": "red blood cell"}, {"bounding_box": {"minimum": {"r": 139, "c": 892}, "maximum": {"r": 217, "c": 999}}, "category": "red blood cell"}, {"bounding_box": {"minimum": {"r": 1042, "c": 448}, "maximum": {"r": 1127, "c": 536}}, "category": "red blood cell"}, {"bounding_box": {"minimum": {"r": 861, "c": 365}, "maximum": {"r": 966, "c": 489}}, "category": "trophozoite"}, {"bounding_box": {"minimum": {"r": 922, "c": 303}, "maximum": {"r": 1010, "c": 412}}, "category": "red blood cell"}, {"bounding_box": {"minimum": {"r": 587, "c": 288}, "maximum": {"r": 677, "c": 389}}, "category": "red blood cell"}, {"bounding_box": {"minimum": {"r": 799, "c": 576}, "maximum": {"r": 888, "c": 672}}, "category": "red blood cell"}, {"bounding_box": {"minimum": {"r": 797, "c": 1376}, "maximum": {"r": 880, "c": 1453}}, "category": "red blood cell"}, {"bounding_box": {"minimum": {"r": 152, "c": 1053}, "maximum": {"r": 271, "c": 1124}}, "category": "red blood cell"}, {"bounding_box": {"minimum": {"r": 509, "c": 1058}, "maximum": {"r": 616, "c": 1163}}, "category": "red blood cell"}, {"bounding_box": {"minimum": {"r": 843, "c": 705}, "maximum": {"r": 942, "c": 806}}, "category": "red blood cell"}, {"bounding_box": {"minimum": {"r": 617, "c": 382}, "maximum": {"r": 712, "c": 476}}, "category": "red blood cell"}, {"bounding_box": {"minimum": {"r": 688, "c": 640}, "maximum": {"r": 806, "c": 752}}, "category": "red blood cell"}, {"bounding_box": {"minimum": {"r": 644, "c": 1072}, "maximum": {"r": 737, "c": 1160}}, "category": "red blood cell"}, {"bounding_box": {"minimum": {"r": 553, "c": 1461}, "maximum": {"r": 641, "c": 1551}}, "category": "red blood cell"}, {"bounding_box": {"minimum": {"r": 957, "c": 95}, "maximum": {"r": 1041, "c": 199}}, "category": "red blood cell"}, {"bounding_box": {"minimum": {"r": 0, "c": 1410}, "maximum": {"r": 100, "c": 1535}}, "category": "red blood cell"}, {"bounding_box": {"minimum": {"r": 239, "c": 285}, "maximum": {"r": 335, "c": 397}}, "category": "red blood cell"}, {"bounding_box": {"minimum": {"r": 1031, "c": 1476}, "maximum": {"r": 1119, "c": 1559}}, "category": "red blood cell"}, {"bounding_box": {"minimum": {"r": 511, "c": 1183}, "maximum": {"r": 606, "c": 1311}}, "category": "red blood cell"}, {"bounding_box": {"minimum": {"r": 714, "c": 1136}, "maximum": {"r": 821, "c": 1242}}, "category": "red blood cell"}, {"bounding_box": {"minimum": {"r": 1013, "c": 7}, "maximum": {"r": 1097, "c": 88}}, "category": "red blood cell"}, {"bounding_box": {"minimum": {"r": 568, "c": 1282}, "maximum": {"r": 647, "c": 1378}}, "category": "red blood cell"}, {"bounding_box": {"minimum": {"r": 30, "c": 940}, "maximum": {"r": 113, "c": 1015}}, "category": "red blood cell"}, {"bounding_box": {"minimum": {"r": 231, "c": 546}, "maximum": {"r": 313, "c": 632}}, "category": "red blood cell"}, {"bounding_box": {"minimum": {"r": 374, "c": 821}, "maximum": {"r": 472, "c": 985}}, "category": "difficult"}, {"bounding_box": {"minimum": {"r": 615, "c": 441}, "maximum": {"r": 714, "c": 554}}, "category": "red blood cell"}, {"bounding_box": {"minimum": {"r": 2, "c": 1073}, "maximum": {"r": 84, "c": 1182}}, "category": "red blood cell"}, {"bounding_box": {"minimum": {"r": 564, "c": 1192}, "maximum": {"r": 673, "c": 1294}}, "category": "red blood cell"}, {"bounding_box": {"minimum": {"r": 764, "c": 1305}, "maximum": {"r": 841, "c": 1385}}, "category": "red blood cell"}, {"bounding_box": {"minimum": {"r": 811, "c": 43}, "maximum": {"r": 884, "c": 143}}, "category": "red blood cell"}, {"bounding_box": {"minimum": {"r": 578, "c": 25}, "maximum": {"r": 659, "c": 102}}, "category": "red blood cell"}, {"bounding_box": {"minimum": {"r": 603, "c": 91}, "maximum": {"r": 680, "c": 186}}, "category": "red blood cell"}, {"bounding_box": {"minimum": {"r": 839, "c": 501}, "maximum": {"r": 918, "c": 585}}, "category": "red blood cell"}, {"bounding_box": {"minimum": {"r": 63, "c": 981}, "maximum": {"r": 165, "c": 1061}}, "category": "red blood cell"}, {"bounding_box": {"minimum": {"r": 1115, "c": 1022}, "maximum": {"r": 1197, "c": 1092}}, "category": "red blood cell"}, {"bounding_box": {"minimum": {"r": 737, "c": 394}, "maximum": {"r": 820, "c": 492}}, "category": "red blood cell"}, {"bounding_box": {"minimum": {"r": 168, "c": 619}, "maximum": {"r": 236, "c": 691}}, "category": "red blood cell"}, {"bounding_box": {"minimum": {"r": 662, "c": 739}, "maximum": {"r": 730, "c": 825}}, "category": "red blood cell"}]