[{"bounding_box": {"minimum": {"r": 750, "c": 877}, "maximum": {"r": 852, "c": 981}}, "category": "red blood cell"}, {"bounding_box": {"minimum": {"r": 437, "c": 497}, "maximum": {"r": 564, "c": 629}}, "category": "red blood cell"}, {"bounding_box": {"minimum": {"r": 271, "c": 1386}, "maximum": {"r": 387, "c": 1496}}, "category": "red blood cell"}, {"bounding_box": {"minimum": {"r": 903, "c": 162}, "maximum": {"r": 1010, "c": 254}}, "category": "red blood cell"}, {"bounding_box": {"minimum": {"r": 837, "c": 266}, "maximum": {"r": 934, "c": 375}}, "category": "red blood cell"}, {"bounding_box": {"minimum": {"r": 612, "c": 863}, "maximum": {"r": 744, "c": 983}}, "category": "red blood cell"}, {"bounding_box": {"minimum": {"r": 963, "c": 1406}, "maximum": {"r": 1088, "c": 1532}}, "category": "red blood cell"}, {"bounding_box": {"minimum": {"r": 289, "c": 1158}, "maximum": {"r": 396, "c": 1262}}, "category": "red blood cell"}, {"bounding_box": {"minimum": {"r": 557, "c": 526}, "maximum": {"r": 658, "c": 638}}, "category": "red blood cell"}, {"bounding_box": {"minimum": {"r": 568, "c": 215}, "maximum": {"r": 677, "c": 327}}, "category": "red blood cell"}, {"bounding_box": {"minimum": {"r": 720, "c": 24}, "maximum": {"r": 839, "c": 150}}, "category": "red blood cell"}, {"bounding_box": {"minimum": {"r": 317, "c": 341}, "maximum": {"r": 424, "c": 445}}, "category": "red blood cell"}, {"bounding_box": {"minimum": {"r": 538, "c": 370}, "maximum": {"r": 654, "c": 489}}, "category": "red blood cell"}, {"bounding_box": {"minimum": {"r": 637, "c": 631}, "maximum": {"r": 752, "c": 749}}, "category": "red blood cell"}, {"bounding_box": {"minimum": {"r": 935, "c": 57}, "maximum": {"r": 1029, "c": 161}}, "category": "red blood cell"}, {"bounding_box": {"minimum": {"r": 1023, "c": 1294}, "maximum": {"r": 1150, "c": 1428}}, "category": "red blood cell"}, {"bounding_box": {"minimum": {"r": 693, "c": 193}, "maximum": {"r": 797, "c": 300}}, "category": "red blood cell"}, {"bounding_box": {"minimum": {"r": 840, "c": 23}, "maximum": {"r": 944, "c": 143}}, "category": "red blood cell"}, {"bounding_box": {"minimum": {"r": 675, "c": 1145}, "maximum": {"r": 801, "c": 1272}}, "category": "red blood cell"}, {"bounding_box": {"minimum": {"r": 735, "c": 689}, "maximum": {"r": 843, "c": 793}}, "category": "red blood cell"}, {"bounding_box": {"minimum": {"r": 375, "c": 1210}, "maximum": {"r": 494, "c": 1340}}, "category": "red blood cell"}, {"bounding_box": {"minimum": {"r": 208, "c": 184}, "maximum": {"r": 306, "c": 295}}, "category": "red blood cell"}, {"bounding_box": {"minimum": {"r": 549, "c": 1203}, "maximum": {"r": 674, "c": 1318}}, "category": "red blood cell"}, {"bounding_box": {"minimum": {"r": 681, "c": 310}, "maximum": {"r": 802, "c": 427}}, "category": "red blood cell"}, {"bounding_box": {"minimum": {"r": 572, "c": 732}, "maximum": {"r": 676, "c": 846}}, "category": "red blood cell"}, {"bounding_box": {"minimum": {"r": 88, "c": 1055}, "maximum": {"r": 209, "c": 1181}}, "category": "red blood cell"}, {"bounding_box": {"minimum": {"r": 520, "c": 811}, "maximum": {"r": 625, "c": 937}}, "category": "red blood cell"}, {"bounding_box": {"minimum": {"r": 856, "c": 457}, "maximum": {"r": 970, "c": 578}}, "category": "red blood cell"}, {"bounding_box": {"minimum": {"r": 167, "c": 440}, "maximum": {"r": 296, "c": 571}}, "category": "red blood cell"}, {"bounding_box": {"minimum": {"r": 289, "c": 1299}, "maximum": {"r": 378, "c": 1378}}, "category": "red blood cell"}, {"bounding_box": {"minimum": {"r": 41, "c": 1384}, "maximum": {"r": 165, "c": 1491}}, "category": "red blood cell"}, {"bounding_box": {"minimum": {"r": 1052, "c": 92}, "maximum": {"r": 1168, "c": 205}}, "category": "red blood cell"}, {"bounding_box": {"minimum": {"r": 146, "c": 832}, "maximum": {"r": 271, "c": 964}}, "category": "red blood cell"}, {"bounding_box": {"minimum": {"r": 578, "c": 420}, "maximum": {"r": 687, "c": 531}}, "category": "red blood cell"}, {"bounding_box": {"minimum": {"r": 877, "c": 858}, "maximum": {"r": 999, "c": 967}}, "category": "red blood cell"}, {"bounding_box": {"minimum": {"r": 517, "c": 1097}, "maximum": {"r": 610, "c": 1206}}, "category": "red blood cell"}, {"bounding_box": {"minimum": {"r": 1035, "c": 191}, "maximum": {"r": 1132, "c": 287}}, "category": "red blood cell"}, {"bounding_box": {"minimum": {"r": 1020, "c": 846}, "maximum": {"r": 1115, "c": 939}}, "category": "red blood cell"}, {"bounding_box": {"minimum": {"r": 1061, "c": 290}, "maximum": {"r": 1151, "c": 389}}, "category": "red blood cell"}, {"bounding_box": {"minimum": {"r": 792, "c": 118}, "maximum": {"r": 909, "c": 227}}, "category": "red blood cell"}, {"bounding_box": {"minimum": {"r": 258, "c": 912}, "maximum": {"r": 360, "c": 1027}}, "category": "red blood cell"}, {"bounding_box": {"minimum": {"r": 830, "c": 791}, "maximum": {"r": 929, "c": 891}}, "category": "red blood cell"}, {"bounding_box": {"minimum": {"r": 904, "c": 1314}, "maximum": {"r": 1027, "c": 1435}}, "category": "red blood cell"}, {"bounding_box": {"minimum": {"r": 453, "c": 1316}, "maximum": {"r": 562, "c": 1426}}, "category": "red blood cell"}, {"bounding_box": {"minimum": {"r": 51, "c": 402}, "maximum": {"r": 154, "c": 506}}, "category": "red blood cell"}, {"bounding_box": {"minimum": {"r": 740, "c": 144}, "maximum": {"r": 854, "c": 269}}, "category": "red blood cell"}, {"bounding_box": {"minimum": {"r": 156, "c": 473}, "maximum": {"r": 261, "c": 577}}, "category": "red blood cell"}, {"bounding_box": {"minimum": {"r": 11, "c": 498}, "maximum": {"r": 123, "c": 603}}, "category": "red blood cell"}, {"bounding_box": {"minimum": {"r": 59, "c": 179}, "maximum": {"r": 168, "c": 297}}, "category": "red blood cell"}, {"bounding_box": {"minimum": {"r": 597, "c": 1037}, "maximum": {"r": 719, "c": 1159}}, "category": "red blood cell"}, {"bounding_box": {"minimum": {"r": 939, "c": 302}, "maximum": {"r": 1048, "c": 426}}, "category": "red blood cell"}, {"bounding_box": {"minimum": {"r": 120, "c": 103}, "maximum": {"r": 240, "c": 207}}, "category": "red blood cell"}, {"bounding_box": {"minimum": {"r": 792, "c": 1258}, "maximum": {"r": 921, "c": 1398}}, "category": "red blood cell"}, {"bounding_box": {"minimum": {"r": 845, "c": 368}, "maximum": {"r": 939, "c": 475}}, "category": "red blood cell"}, {"bounding_box": {"minimum": {"r": 421, "c": 1112}, "maximum": {"r": 532, "c": 1214}}, "category": "red blood cell"}, {"bounding_box": {"minimum": {"r": 35, "c": 805}, "maximum": {"r": 129, "c": 917}}, "category": "red blood cell"}, {"bounding_box": {"minimum": {"r": 142, "c": 937}, "maximum": {"r": 232, "c": 1021}}, "category": "red blood cell"}, {"bounding_box": {"minimum": {"r": 515, "c": 1294}, "maximum": {"r": 623, "c": 1401}}, "category": "red blood cell"}, {"bounding_box": {"minimum": {"r": 215, "c": 1031}, "maximum": {"r": 333, "c": 1136}}, "category": "red blood cell"}, {"bounding_box": {"minimum": {"r": 919, "c": 1227}, "maximum": {"r": 1034, "c": 1361}}, "category": "red blood cell"}, {"bounding_box": {"minimum": {"r": 476, "c": 1412}, "maximum": {"r": 593, "c": 1521}}, "category": "red blood cell"}, {"bounding_box": {"minimum": {"r": 98, "c": 1241}, "maximum": {"r": 203, "c": 1352}}, "category": "red blood cell"}, {"bounding_box": {"minimum": {"r": 113, "c": 673}, "maximum": {"r": 230, "c": 785}}, "category": "red blood cell"}, {"bounding_box": {"minimum": {"r": 406, "c": 757}, "maximum": {"r": 503, "c": 886}}, "category": "red blood cell"}, {"bounding_box": {"minimum": {"r": 508, "c": 646}, "maximum": {"r": 626, "c": 743}}, "category": "red blood cell"}, {"bounding_box": {"minimum": {"r": 935, "c": 361}, "maximum": {"r": 1047, "c": 478}}, "category": "red blood cell"}, {"bounding_box": {"minimum": {"r": 64, "c": 585}, "maximum": {"r": 171, "c": 723}}, "category": "red blood cell"}, {"bounding_box": {"minimum": {"r": 132, "c": 1221}, "maximum": {"r": 248, "c": 1316}}, "category": "red blood cell"}, {"bounding_box": {"minimum": {"r": 233, "c": 295}, "maximum": {"r": 331, "c": 381}}, "category": "red blood cell"}, {"bounding_box": {"minimum": {"r": 597, "c": 177}, "maximum": {"r": 693, "c": 282}}, "category": "red blood cell"}, {"bounding_box": {"minimum": {"r": 494, "c": 192}, "maximum": {"r": 578, "c": 282}}, "category": "red blood cell"}, {"bounding_box": {"minimum": {"r": 385, "c": 210}, "maximum": {"r": 486, "c": 310}}, "category": "red blood cell"}, {"bounding_box": {"minimum": {"r": 377, "c": 162}, "maximum": {"r": 486, "c": 255}}, "category": "red blood cell"}, {"bounding_box": {"minimum": {"r": 299, "c": 233}, "maximum": {"r": 400, "c": 327}}, "category": "red blood cell"}, {"bounding_box": {"minimum": {"r": 483, "c": 682}, "maximum": {"r": 584, "c": 836}}, "category": "trophozoite"}, {"bounding_box": {"minimum": {"r": 248, "c": 111}, "maximum": {"r": 428, "c": 254}}, "category": "trophozoite"}, {"bounding_box": {"minimum": {"r": 468, "c": 115}, "maximum": {"r": 648, "c": 212}}, "category": "trophozoite"}, {"bounding_box": {"minimum": {"r": 75, "c": 1318}, "maximum": {"r": 203, "c": 1425}}, "category": "trophozoite"}, {"bounding_box": {"minimum": {"r": 372, "c": 1467}, "maximum": {"r": 468, "c": 1566}}, "category": "red blood cell"}, {"bounding_box": {"minimum": {"r": 137, "c": 988}, "maximum": {"r": 246, "c": 1089}}, "category": "red blood cell"}, {"bounding_box": {"minimum": {"r": 267, "c": 1057}, "maximum": {"r": 368, "c": 1179}}, "category": "red blood cell"}, {"bounding_box": {"minimum": {"r": 984, "c": 744}, "maximum": {"r": 1080, "c": 869}}, "category": "red blood cell"}, {"bounding_box": {"minimum": {"r": 1008, "c": 633}, "maximum": {"r": 1110, "c": 729}}, "category": "red blood cell"}, {"bounding_box": {"minimum": {"r": 477, "c": 1476}, "maximum": {"r": 573, "c": 1587}}, "category": "red blood cell"}, {"bounding_box": {"minimum": {"r": 195, "c": 1315}, "maximum": {"r": 291, "c": 1399}}, "category": "red blood cell"}, {"bounding_box": {"minimum": {"r": 180, "c": 1268}, "maximum": {"r": 299, "c": 1371}}, "category": "red blood cell"}, {"bounding_box": {"minimum": {"r": 605, "c": 1104}, "maximum": {"r": 719, "c": 1215}}, "category": "red blood cell"}, {"bounding_box": {"minimum": {"r": 582, "c": 1388}, "maximum": {"r": 700, "c": 1489}}, "category": "red blood cell"}]