[{"bounding_box": {"minimum": {"r": 427, "c": 1313}, "maximum": {"r": 532, "c": 1410}}, "category": "red blood cell"}, {"bounding_box": {"minimum": {"r": 826, "c": 1146}, "maximum": {"r": 944, "c": 1252}}, "category": "red blood cell"}, {"bounding_box": {"minimum": {"r": 859, "c": 362}, "maximum": {"r": 983, "c": 490}}, "category": "red blood cell"}, {"bounding_box": {"minimum": {"r": 389, "c": 532}, "maximum": {"r": 499, "c": 638}}, "category": "red blood cell"}, {"bounding_box": {"minimum": {"r": 485, "c": 125}, "maximum": {"r": 594, "c": 235}}, "category": "red blood cell"}, {"bounding_box": {"minimum": {"r": 395, "c": 930}, "maximum": {"r": 502, "c": 1042}}, "category": "red blood cell"}, {"bounding_box": {"minimum": {"r": 889, "c": 807}, "maximum": {"r": 995, "c": 904}}, "category": "red blood cell"}, {"bounding_box": {"minimum": {"r": 742, "c": 259}, "maximum": {"r": 857, "c": 392}}, "category": "difficult"}, {"bounding_box": {"minimum": {"r": 725, "c": 870}, "maximum": {"r": 831, "c": 967}}, "category": "red blood cell"}, {"bounding_box": {"minimum": {"r": 978, "c": 1225}, "maximum": {"r": 1097, "c": 1341}}, "category": "red blood cell"}, {"bounding_box": {"minimum": {"r": 319, "c": 50}, "maximum": {"r": 427, "c": 144}}, "category": "red blood cell"}, {"bounding_box": {"minimum": {"r": 389, "c": 1409}, "maximum": {"r": 484, "c": 1498}}, "category": "red blood cell"}, {"bounding_box": {"minimum": {"r": 932, "c": 727}, "maximum": {"r": 1039, "c": 834}}, "category": "red blood cell"}, {"bounding_box": {"minimum": {"r": 62, "c": 520}, "maximum": {"r": 174, "c": 636}}, "category": "red blood cell"}, {"bounding_box": {"minimum": {"r": 819, "c": 643}, "maximum": {"r": 942, "c": 781}}, "category": "red blood cell"}, {"bounding_box": {"minimum": {"r": 101, "c": 387}, "maximum": {"r": 196, "c": 496}}, "category": "red blood cell"}, {"bounding_box": {"minimum": {"r": 842, "c": 1411}, "maximum": {"r": 949, "c": 1514}}, "category": "red blood cell"}, {"bounding_box": {"minimum": {"r": 113, "c": 1052}, "maximum": {"r": 196, "c": 1181}}, "category": "red blood cell"}, {"bounding_box": {"minimum": {"r": 507, "c": 613}, "maximum": {"r": 610, "c": 717}}, "category": "red blood cell"}, {"bounding_box": {"minimum": {"r": 810, "c": 496}, "maximum": {"r": 920, "c": 607}}, "category": "red blood cell"}, {"bounding_box": {"minimum": {"r": 1034, "c": 129}, "maximum": {"r": 1139, "c": 232}}, "category": "red blood cell"}, {"bounding_box": {"minimum": {"r": 633, "c": 845}, "maximum": {"r": 736, "c": 953}}, "category": "red blood cell"}, {"bounding_box": {"minimum": {"r": 191, "c": 1432}, "maximum": {"r": 314, "c": 1555}}, "category": "red blood cell"}, {"bounding_box": {"minimum": {"r": 1074, "c": 913}, "maximum": {"r": 1176, "c": 1026}}, "category": "red blood cell"}, {"bounding_box": {"minimum": {"r": 262, "c": 37}, "maximum": {"r": 327, "c": 157}}, "category": "red blood cell"}, {"bounding_box": {"minimum": {"r": 659, "c": 1111}, "maximum": {"r": 764, "c": 1203}}, "category": "red blood cell"}, {"bounding_box": {"minimum": {"r": 272, "c": 1091}, "maximum": {"r": 373, "c": 1187}}, "category": "red blood cell"}, {"bounding_box": {"minimum": {"r": 710, "c": 995}, "maximum": {"r": 834, "c": 1094}}, "category": "red blood cell"}, {"bounding_box": {"minimum": {"r": 681, "c": 1247}, "maximum": {"r": 788, "c": 1354}}, "category": "red blood cell"}, {"bounding_box": {"minimum": {"r": 790, "c": 1319}, "maximum": {"r": 886, "c": 1413}}, "category": "red blood cell"}, {"bounding_box": {"minimum": {"r": 1027, "c": 439}, "maximum": {"r": 1123, "c": 545}}, "category": "red blood cell"}, {"bounding_box": {"minimum": {"r": 143, "c": 1279}, "maximum": {"r": 261, "c": 1383}}, "category": "red blood cell"}, {"bounding_box": {"minimum": {"r": 339, "c": 944}, "maximum": {"r": 437, "c": 1061}}, "category": "red blood cell"}, {"bounding_box": {"minimum": {"r": 824, "c": 221}, "maximum": {"r": 919, "c": 331}}, "category": "red blood cell"}, {"bounding_box": {"minimum": {"r": 168, "c": 269}, "maximum": {"r": 276, "c": 374}}, "category": "red blood cell"}, {"bounding_box": {"minimum": {"r": 1063, "c": 808}, "maximum": {"r": 1178, "c": 911}}, "category": "red blood cell"}, {"bounding_box": {"minimum": {"r": 600, "c": 564}, "maximum": {"r": 709, "c": 670}}, "category": "red blood cell"}, {"bounding_box": {"minimum": {"r": 340, "c": 714}, "maximum": {"r": 442, "c": 810}}, "category": "red blood cell"}, {"bounding_box": {"minimum": {"r": 658, "c": 634}, "maximum": {"r": 796, "c": 743}}, "category": "red blood cell"}, {"bounding_box": {"minimum": {"r": 460, "c": 331}, "maximum": {"r": 553, "c": 428}}, "category": "red blood cell"}, {"bounding_box": {"minimum": {"r": 948, "c": 469}, "maximum": {"r": 1056, "c": 579}}, "category": "red blood cell"}, {"bounding_box": {"minimum": {"r": 889, "c": 939}, "maximum": {"r": 1005, "c": 1040}}, "category": "red blood cell"}, {"bounding_box": {"minimum": {"r": 941, "c": 1017}, "maximum": {"r": 1030, "c": 1112}}, "category": "red blood cell"}, {"bounding_box": {"minimum": {"r": 107, "c": 1129}, "maximum": {"r": 242, "c": 1239}}, "category": "red blood cell"}, {"bounding_box": {"minimum": {"r": 394, "c": 322}, "maximum": {"r": 500, "c": 434}}, "category": "red blood cell"}, {"bounding_box": {"minimum": {"r": 367, "c": 434}, "maximum": {"r": 512, "c": 532}}, "category": "red blood cell"}, {"bounding_box": {"minimum": {"r": 610, "c": 1456}, "maximum": {"r": 718, "c": 1573}}, "category": "red blood cell"}, {"bounding_box": {"minimum": {"r": 837, "c": 871}, "maximum": {"r": 947, "c": 965}}, "category": "red blood cell"}, {"bounding_box": {"minimum": {"r": 113, "c": 134}, "maximum": {"r": 220, "c": 242}}, "category": "red blood cell"}, {"bounding_box": {"minimum": {"r": 231, "c": 1291}, "maximum": {"r": 346, "c": 1404}}, "category": "red blood cell"}, {"bounding_box": {"minimum": {"r": 25, "c": 1049}, "maximum": {"r": 114, "c": 1166}}, "category": "red blood cell"}, {"bounding_box": {"minimum": {"r": 103, "c": 1475}, "maximum": {"r": 233, "c": 1581}}, "category": "red blood cell"}, {"bounding_box": {"minimum": {"r": 153, "c": 1074}, "maximum": {"r": 262, "c": 1177}}, "category": "red blood cell"}, {"bounding_box": {"minimum": {"r": 76, "c": 62}, "maximum": {"r": 199, "c": 167}}, "category": "red blood cell"}, {"bounding_box": {"minimum": {"r": 619, "c": 642}, "maximum": {"r": 721, "c": 753}}, "category": "red blood cell"}, {"bounding_box": {"minimum": {"r": 9, "c": 213}, "maximum": {"r": 112, "c": 321}}, "category": "red blood cell"}, {"bounding_box": {"minimum": {"r": 1078, "c": 288}, "maximum": {"r": 1183, "c": 384}}, "category": "red blood cell"}, {"bounding_box": {"minimum": {"r": 195, "c": 109}, "maximum": {"r": 275, "c": 231}}, "category": "red blood cell"}, {"bounding_box": {"minimum": {"r": 1084, "c": 77}, "maximum": {"r": 1164, "c": 174}}, "category": "red blood cell"}, {"bounding_box": {"minimum": {"r": 798, "c": 1505}, "maximum": {"r": 907, "c": 1600}}, "category": "red blood cell"}, {"bounding_box": {"minimum": {"r": 929, "c": 1505}, "maximum": {"r": 1032, "c": 1600}}, "category": "red blood cell"}]