[{"bounding_box": {"minimum": {"r": 590, "c": 126}, "maximum": {"r": 692, "c": 222}}, "category": "red blood cell"}, {"bounding_box": {"minimum": {"r": 300, "c": 1182}, "maximum": {"r": 399, "c": 1279}}, "category": "red blood cell"}, {"bounding_box": {"minimum": {"r": 353, "c": 1083}, "maximum": {"r": 465, "c": 1195}}, "category": "red blood cell"}, {"bounding_box": {"minimum": {"r": 92, "c": 157}, "maximum": {"r": 192, "c": 256}}, "category": "red blood cell"}, {"bounding_box": {"minimum": {"r": 108, "c": 980}, "maximum": {"r": 211, "c": 1084}}, "category": "red blood cell"}, {"bounding_box": {"minimum": {"r": 43, "c": 1151}, "maximum": {"r": 158, "c": 1269}}, "category": "red blood cell"}, {"bounding_box": {"minimum": {"r": 224, "c": 953}, "maximum": {"r": 321, "c": 1052}}, "category": "red blood cell"}, {"bounding_box": {"minimum": {"r": 70, "c": 572}, "maximum": {"r": 175, "c": 675}}, "category": "red blood cell"}, {"bounding_box": {"minimum": {"r": 669, "c": 743}, "maximum": {"r": 779, "c": 853}}, "category": "red blood cell"}, {"bounding_box": {"minimum": {"r": 506, "c": 847}, "maximum": {"r": 632, "c": 963}}, "category": "red blood cell"}, {"bounding_box": {"minimum": {"r": 804, "c": 23}, "maximum": {"r": 910, "c": 122}}, "category": "red blood cell"}, {"bounding_box": {"minimum": {"r": 410, "c": 1448}, "maximum": {"r": 519, "c": 1546}}, "category": "red blood cell"}, {"bounding_box": {"minimum": {"r": 729, "c": 1277}, "maximum": {"r": 844, "c": 1385}}, "category": "red blood cell"}, {"bounding_box": {"minimum": {"r": 967, "c": 824}, "maximum": {"r": 1087, "c": 936}}, "category": "red blood cell"}, {"bounding_box": {"minimum": {"r": 132, "c": 842}, "maximum": {"r": 237, "c": 945}}, "category": "red blood cell"}, {"bounding_box": {"minimum": {"r": 902, "c": 445}, "maximum": {"r": 1016, "c": 563}}, "category": "red blood cell"}, {"bounding_box": {"minimum": {"r": 782, "c": 850}, "maximum": {"r": 896, "c": 952}}, "category": "red blood cell"}, {"bounding_box": {"minimum": {"r": 886, "c": 918}, "maximum": {"r": 1001, "c": 1025}}, "category": "red blood cell"}, {"bounding_box": {"minimum": {"r": 488, "c": 295}, "maximum": {"r": 603, "c": 408}}, "category": "red blood cell"}, {"bounding_box": {"minimum": {"r": 910, "c": 272}, "maximum": {"r": 1008, "c": 378}}, "category": "red blood cell"}, {"bounding_box": {"minimum": {"r": 787, "c": 971}, "maximum": {"r": 904, "c": 1081}}, "category": "red blood cell"}, {"bounding_box": {"minimum": {"r": 458, "c": 1034}, "maximum": {"r": 559, "c": 1146}}, "category": "red blood cell"}, {"bounding_box": {"minimum": {"r": 712, "c": 1401}, "maximum": {"r": 834, "c": 1513}}, "category": "red blood cell"}, {"bounding_box": {"minimum": {"r": 789, "c": 269}, "maximum": {"r": 903, "c": 396}}, "category": "red blood cell"}, {"bounding_box": {"minimum": {"r": 103, "c": 376}, "maximum": {"r": 223, "c": 491}}, "category": "red blood cell"}, {"bounding_box": {"minimum": {"r": 337, "c": 318}, "maximum": {"r": 452, "c": 429}}, "category": "red blood cell"}, {"bounding_box": {"minimum": {"r": 393, "c": 1352}, "maximum": {"r": 495, "c": 1442}}, "category": "red blood cell"}, {"bounding_box": {"minimum": {"r": 763, "c": 458}, "maximum": {"r": 852, "c": 553}}, "category": "red blood cell"}, {"bounding_box": {"minimum": {"r": 978, "c": 1364}, "maximum": {"r": 1071, "c": 1464}}, "category": "red blood cell"}, {"bounding_box": {"minimum": {"r": 1009, "c": 149}, "maximum": {"r": 1123, "c": 277}}, "category": "red blood cell"}, {"bounding_box": {"minimum": {"r": 463, "c": 1257}, "maximum": {"r": 575, "c": 1358}}, "category": "red blood cell"}, {"bounding_box": {"minimum": {"r": 852, "c": 1093}, "maximum": {"r": 987, "c": 1212}}, "category": "red blood cell"}, {"bounding_box": {"minimum": {"r": 107, "c": 681}, "maximum": {"r": 233, "c": 801}}, "category": "red blood cell"}, {"bounding_box": {"minimum": {"r": 240, "c": 1402}, "maximum": {"r": 362, "c": 1523}}, "category": "red blood cell"}, {"bounding_box": {"minimum": {"r": 52, "c": 1287}, "maximum": {"r": 172, "c": 1407}}, "category": "red blood cell"}, {"bounding_box": {"minimum": {"r": 35, "c": 1386}, "maximum": {"r": 136, "c": 1494}}, "category": "red blood cell"}, {"bounding_box": {"minimum": {"r": 744, "c": 610}, "maximum": {"r": 871, "c": 722}}, "category": "red blood cell"}, {"bounding_box": {"minimum": {"r": 566, "c": 394}, "maximum": {"r": 706, "c": 515}}, "category": "red blood cell"}, {"bounding_box": {"minimum": {"r": 891, "c": 1339}, "maximum": {"r": 985, "c": 1451}}, "category": "red blood cell"}, {"bounding_box": {"minimum": {"r": 829, "c": 771}, "maximum": {"r": 947, "c": 885}}, "category": "red blood cell"}, {"bounding_box": {"minimum": {"r": 191, "c": 509}, "maximum": {"r": 308, "c": 627}}, "category": "red blood cell"}, {"bounding_box": {"minimum": {"r": 575, "c": 1146}, "maximum": {"r": 675, "c": 1259}}, "category": "red blood cell"}, {"bounding_box": {"minimum": {"r": 408, "c": 899}, "maximum": {"r": 492, "c": 1011}}, "category": "red blood cell"}, {"bounding_box": {"minimum": {"r": 619, "c": 252}, "maximum": {"r": 747, "c": 372}}, "category": "red blood cell"}, {"bounding_box": {"minimum": {"r": 202, "c": 2}, "maximum": {"r": 326, "c": 97}}, "category": "red blood cell"}, {"bounding_box": {"minimum": {"r": 315, "c": 856}, "maximum": {"r": 423, "c": 981}}, "category": "red blood cell"}, {"bounding_box": {"minimum": {"r": 1029, "c": 1430}, "maximum": {"r": 1158, "c": 1544}}, "category": "red blood cell"}, {"bounding_box": {"minimum": {"r": 462, "c": 671}, "maximum": {"r": 566, "c": 792}}, "category": "red blood cell"}, {"bounding_box": {"minimum": {"r": 245, "c": 89}, "maximum": {"r": 381, "c": 192}}, "category": "red blood cell"}, {"bounding_box": {"minimum": {"r": 644, "c": 1077}, "maximum": {"r": 756, "c": 1188}}, "category": "red blood cell"}, {"bounding_box": {"minimum": {"r": 630, "c": 494}, "maximum": {"r": 748, "c": 597}}, "category": "red blood cell"}, {"bounding_box": {"minimum": {"r": 920, "c": 695}, "maximum": {"r": 1045, "c": 815}}, "category": "red blood cell"}, {"bounding_box": {"minimum": {"r": 981, "c": 1260}, "maximum": {"r": 1129, "c": 1381}}, "category": "red blood cell"}, {"bounding_box": {"minimum": {"r": 967, "c": 652}, "maximum": {"r": 1103, "c": 769}}, "category": "red blood cell"}, {"bounding_box": {"minimum": {"r": 977, "c": 572}, "maximum": {"r": 1119, "c": 666}}, "category": "red blood cell"}, {"bounding_box": {"minimum": {"r": 913, "c": 1442}, "maximum": {"r": 1029, "c": 1548}}, "category": "red blood cell"}, {"bounding_box": {"minimum": {"r": 118, "c": 1447}, "maximum": {"r": 206, "c": 1556}}, "category": "red blood cell"}, {"bounding_box": {"minimum": {"r": 685, "c": 1147}, "maximum": {"r": 820, "c": 1284}}, "category": "red blood cell"}, {"bounding_box": {"minimum": {"r": 229, "c": 1476}, "maximum": {"r": 334, "c": 1593}}, "category": "red blood cell"}, {"bounding_box": {"minimum": {"r": 625, "c": 1001}, "maximum": {"r": 791, "c": 1102}}, "category": "red blood cell"}, {"bounding_box": {"minimum": {"r": 908, "c": 1504}, "maximum": {"r": 1020, "c": 1598}}, "category": "red blood cell"}, {"bounding_box": {"minimum": {"r": 363, "c": 693}, "maximum": {"r": 489, "c": 843}}, "category": "trophozoite"}, {"bounding_box": {"minimum": {"r": 804, "c": 672}, "maximum": {"r": 928, "c": 809}}, "category": "red blood cell"}, {"bounding_box": {"minimum": {"r": 1015, "c": 496}, "maximum": {"r": 1175, "c": 620}}, "category": "red blood cell"}]