[{"bounding_box": {"minimum": {"r": 736, "c": 1392}, "maximum": {"r": 837, "c": 1492}}, "category": "red blood cell"}, {"bounding_box": {"minimum": {"r": 1001, "c": 468}, "maximum": {"r": 1124, "c": 592}}, "category": "red blood cell"}, {"bounding_box": {"minimum": {"r": 579, "c": 1249}, "maximum": {"r": 675, "c": 1353}}, "category": "red blood cell"}, {"bounding_box": {"minimum": {"r": 921, "c": 329}, "maximum": {"r": 1024, "c": 440}}, "category": "red blood cell"}, {"bounding_box": {"minimum": {"r": 511, "c": 630}, "maximum": {"r": 603, "c": 735}}, "category": "red blood cell"}, {"bounding_box": {"minimum": {"r": 100, "c": 195}, "maximum": {"r": 214, "c": 305}}, "category": "red blood cell"}, {"bounding_box": {"minimum": {"r": 427, "c": 1054}, "maximum": {"r": 531, "c": 1152}}, "category": "red blood cell"}, {"bounding_box": {"minimum": {"r": 577, "c": 1039}, "maximum": {"r": 693, "c": 1146}}, "category": "red blood cell"}, {"bounding_box": {"minimum": {"r": 611, "c": 557}, "maximum": {"r": 726, "c": 667}}, "category": "red blood cell"}, {"bounding_box": {"minimum": {"r": 872, "c": 717}, "maximum": {"r": 1016, "c": 822}}, "category": "red blood cell"}, {"bounding_box": {"minimum": {"r": 379, "c": 502}, "maximum": {"r": 489, "c": 616}}, "category": "red blood cell"}, {"bounding_box": {"minimum": {"r": 309, "c": 960}, "maximum": {"r": 410, "c": 1073}}, "category": "red blood cell"}, {"bounding_box": {"minimum": {"r": 279, "c": 1140}, "maximum": {"r": 379, "c": 1250}}, "category": "red blood cell"}, {"bounding_box": {"minimum": {"r": 267, "c": 517}, "maximum": {"r": 380, "c": 633}}, "category": "red blood cell"}, {"bounding_box": {"minimum": {"r": 993, "c": 191}, "maximum": {"r": 1099, "c": 307}}, "category": "red blood cell"}, {"bounding_box": {"minimum": {"r": 117, "c": 1100}, "maximum": {"r": 221, "c": 1215}}, "category": "red blood cell"}, {"bounding_box": {"minimum": {"r": 118, "c": 651}, "maximum": {"r": 238, "c": 769}}, "category": "red blood cell"}, {"bounding_box": {"minimum": {"r": 70, "c": 55}, "maximum": {"r": 183, "c": 181}}, "category": "red blood cell"}, {"bounding_box": {"minimum": {"r": 1015, "c": 958}, "maximum": {"r": 1134, "c": 1075}}, "category": "red blood cell"}, {"bounding_box": {"minimum": {"r": 935, "c": 609}, "maximum": {"r": 1029, "c": 713}}, "category": "red blood cell"}, {"bounding_box": {"minimum": {"r": 794, "c": 1004}, "maximum": {"r": 900, "c": 1115}}, "category": "red blood cell"}, {"bounding_box": {"minimum": {"r": 612, "c": 664}, "maximum": {"r": 709, "c": 755}}, "category": "red blood cell"}, {"bounding_box": {"minimum": {"r": 455, "c": 327}, "maximum": {"r": 567, "c": 441}}, "category": "red blood cell"}, {"bounding_box": {"minimum": {"r": 924, "c": 98}, "maximum": {"r": 1041, "c": 214}}, "category": "red blood cell"}, {"bounding_box": {"minimum": {"r": 818, "c": 206}, "maximum": {"r": 945, "c": 320}}, "category": "red blood cell"}, {"bounding_box": {"minimum": {"r": 39, "c": 789}, "maximum": {"r": 137, "c": 890}}, "category": "red blood cell"}, {"bounding_box": {"minimum": {"r": 89, "c": 1364}, "maximum": {"r": 188, "c": 1475}}, "category": "red blood cell"}, {"bounding_box": {"minimum": {"r": 754, "c": 411}, "maximum": {"r": 867, "c": 526}}, "category": "red blood cell"}, {"bounding_box": {"minimum": {"r": 183, "c": 1310}, "maximum": {"r": 286, "c": 1401}}, "category": "red blood cell"}, {"bounding_box": {"minimum": {"r": 291, "c": 715}, "maximum": {"r": 406, "c": 825}}, "category": "red blood cell"}, {"bounding_box": {"minimum": {"r": 502, "c": 474}, "maximum": {"r": 607, "c": 584}}, "category": "red blood cell"}, {"bounding_box": {"minimum": {"r": 1027, "c": 1076}, "maximum": {"r": 1141, "c": 1192}}, "category": "red blood cell"}, {"bounding_box": {"minimum": {"r": 1063, "c": 771}, "maximum": {"r": 1168, "c": 879}}, "category": "red blood cell"}, {"bounding_box": {"minimum": {"r": 650, "c": 759}, "maximum": {"r": 757, "c": 878}}, "category": "red blood cell"}, {"bounding_box": {"minimum": {"r": 1088, "c": 883}, "maximum": {"r": 1173, "c": 1002}}, "category": "red blood cell"}, {"bounding_box": {"minimum": {"r": 329, "c": 338}, "maximum": {"r": 443, "c": 479}}, "category": "difficult"}, {"bounding_box": {"minimum": {"r": 746, "c": 773}, "maximum": {"r": 830, "c": 859}}, "category": "red blood cell"}, {"bounding_box": {"minimum": {"r": 575, "c": 14}, "maximum": {"r": 671, "c": 120}}, "category": "red blood cell"}, {"bounding_box": {"minimum": {"r": 661, "c": 378}, "maximum": {"r": 791, "c": 490}}, "category": "red blood cell"}, {"bounding_box": {"minimum": {"r": 197, "c": 1448}, "maximum": {"r": 276, "c": 1552}}, "category": "red blood cell"}, {"bounding_box": {"minimum": {"r": 960, "c": 1023}, "maximum": {"r": 1042, "c": 1131}}, "category": "red blood cell"}, {"bounding_box": {"minimum": {"r": 838, "c": 296}, "maximum": {"r": 932, "c": 407}}, "category": "red blood cell"}, {"bounding_box": {"minimum": {"r": 124, "c": 401}, "maximum": {"r": 208, "c": 538}}, "category": "red blood cell"}, {"bounding_box": {"minimum": {"r": 170, "c": 1473}, "maximum": {"r": 272, "c": 1595}}, "category": "red blood cell"}, {"bounding_box": {"minimum": {"r": 172, "c": 378}, "maximum": {"r": 258, "c": 517}}, "category": "red blood cell"}, {"bounding_box": {"minimum": {"r": 738, "c": 855}, "maximum": {"r": 830, "c": 985}}, "category": "red blood cell"}, {"bounding_box": {"minimum": {"r": 434, "c": 1135}, "maximum": {"r": 511, "c": 1217}}, "category": "red blood cell"}]