[{"bounding_box": {"minimum": {"r": 731, "c": 1183}, "maximum": {"r": 842, "c": 1300}}, "category": "red blood cell"}, {"bounding_box": {"minimum": {"r": 1022, "c": 1340}, "maximum": {"r": 1134, "c": 1443}}, "category": "red blood cell"}, {"bounding_box": {"minimum": {"r": 690, "c": 32}, "maximum": {"r": 789, "c": 124}}, "category": "red blood cell"}, {"bounding_box": {"minimum": {"r": 506, "c": 107}, "maximum": {"r": 624, "c": 210}}, "category": "red blood cell"}, {"bounding_box": {"minimum": {"r": 765, "c": 223}, "maximum": {"r": 899, "c": 334}}, "category": "red blood cell"}, {"bounding_box": {"minimum": {"r": 1064, "c": 1037}, "maximum": {"r": 1176, "c": 1165}}, "category": "red blood cell"}, {"bounding_box": {"minimum": {"r": 161, "c": 995}, "maximum": {"r": 271, "c": 1097}}, "category": "red blood cell"}, {"bounding_box": {"minimum": {"r": 718, "c": 743}, "maximum": {"r": 830, "c": 862}}, "category": "red blood cell"}, {"bounding_box": {"minimum": {"r": 93, "c": 192}, "maximum": {"r": 219, "c": 294}}, "category": "red blood cell"}, {"bounding_box": {"minimum": {"r": 846, "c": 743}, "maximum": {"r": 961, "c": 845}}, "category": "red blood cell"}, {"bounding_box": {"minimum": {"r": 196, "c": 528}, "maximum": {"r": 324, "c": 627}}, "category": "red blood cell"}, {"bounding_box": {"minimum": {"r": 107, "c": 1356}, "maximum": {"r": 214, "c": 1456}}, "category": "red blood cell"}, {"bounding_box": {"minimum": {"r": 313, "c": 48}, "maximum": {"r": 413, "c": 164}}, "category": "red blood cell"}, {"bounding_box": {"minimum": {"r": 935, "c": 1262}, "maximum": {"r": 1034, "c": 1368}}, "category": "red blood cell"}, {"bounding_box": {"minimum": {"r": 576, "c": 422}, "maximum": {"r": 700, "c": 521}}, "category": "red blood cell"}, {"bounding_box": {"minimum": {"r": 361, "c": 862}, "maximum": {"r": 484, "c": 967}}, "category": "red blood cell"}, {"bounding_box": {"minimum": {"r": 685, "c": 1296}, "maximum": {"r": 796, "c": 1407}}, "category": "red blood cell"}, {"bounding_box": {"minimum": {"r": 1040, "c": 878}, "maximum": {"r": 1148, "c": 985}}, "category": "red blood cell"}, {"bounding_box": {"minimum": {"r": 798, "c": 640}, "maximum": {"r": 920, "c": 741}}, "category": "red blood cell"}, {"bounding_box": {"minimum": {"r": 502, "c": 293}, "maximum": {"r": 629, "c": 390}}, "category": "red blood cell"}, {"bounding_box": {"minimum": {"r": 1046, "c": 505}, "maximum": {"r": 1157, "c": 618}}, "category": "red blood cell"}, {"bounding_box": {"minimum": {"r": 96, "c": 1232}, "maximum": {"r": 214, "c": 1350}}, "category": "red blood cell"}, {"bounding_box": {"minimum": {"r": 492, "c": 838}, "maximum": {"r": 600, "c": 959}}, "category": "red blood cell"}, {"bounding_box": {"minimum": {"r": 512, "c": 694}, "maximum": {"r": 632, "c": 796}}, "category": "red blood cell"}, {"bounding_box": {"minimum": {"r": 570, "c": 1343}, "maximum": {"r": 687, "c": 1459}}, "category": "red blood cell"}, {"bounding_box": {"minimum": {"r": 91, "c": 690}, "maximum": {"r": 193, "c": 782}}, "category": "red blood cell"}, {"bounding_box": {"minimum": {"r": 484, "c": 499}, "maximum": {"r": 598, "c": 615}}, "category": "red blood cell"}, {"bounding_box": {"minimum": {"r": 691, "c": 137}, "maximum": {"r": 803, "c": 231}}, "category": "red blood cell"}, {"bounding_box": {"minimum": {"r": 958, "c": 236}, "maximum": {"r": 1071, "c": 345}}, "category": "red blood cell"}, {"bounding_box": {"minimum": {"r": 599, "c": 968}, "maximum": {"r": 711, "c": 1079}}, "category": "red blood cell"}, {"bounding_box": {"minimum": {"r": 242, "c": 824}, "maximum": {"r": 371, "c": 918}}, "category": "red blood cell"}, {"bounding_box": {"minimum": {"r": 214, "c": 619}, "maximum": {"r": 341, "c": 727}}, "category": "red blood cell"}, {"bounding_box": {"minimum": {"r": 165, "c": 646}, "maximum": {"r": 279, "c": 761}}, "category": "red blood cell"}, {"bounding_box": {"minimum": {"r": 807, "c": 1383}, "maximum": {"r": 941, "c": 1517}}, "category": "difficult"}, {"bounding_box": {"minimum": {"r": 506, "c": 1336}, "maximum": {"r": 606, "c": 1461}}, "category": "red blood cell"}, {"bounding_box": {"minimum": {"r": 896, "c": 263}, "maximum": {"r": 1030, "c": 368}}, "category": "red blood cell"}, {"bounding_box": {"minimum": {"r": 534, "c": 790}, "maximum": {"r": 660, "c": 890}}, "category": "red blood cell"}, {"bounding_box": {"minimum": {"r": 987, "c": 1416}, "maximum": {"r": 1126, "c": 1538}}, "category": "difficult"}, {"bounding_box": {"minimum": {"r": 52, "c": 21}, "maximum": {"r": 176, "c": 113}}, "category": "red blood cell"}, {"bounding_box": {"minimum": {"r": 947, "c": 597}, "maximum": {"r": 1045, "c": 701}}, "category": "red blood cell"}, {"bounding_box": {"minimum": {"r": 66, "c": 104}, "maximum": {"r": 240, "c": 195}}, "category": "trophozoite"}, {"bounding_box": {"minimum": {"r": 145, "c": 2}, "maximum": {"r": 283, "c": 113}}, "category": "red blood cell"}]